cosmodules/__init__.py
cosmodules/classification/__init__.py
cosmodules/classification/active_learning.py
cosmodules/classification/label_merging.py
cosmodules/classification/output_analysis.py
cosmodules/classification/output_analysis.yaml
cosmodules/detection/__init__.py
cosmodules/detection/active_learning.py
cosmodules/detection/format_conversion.py
cosmodules/detection/label_merging.py
cosmodules/detection/output_analysis.py
cosmodules/detection/output_analysis.yaml
cosmodules/detection/visualization.py
cosmodules/segmentation/__init__.py
cosmodules/segmentation/active_learning.py
cosmodules/segmentation/format_conversion.py
cosmodules/segmentation/output_analysis.py
cosmodules/segmentation/output_analysis_instance.yaml
cosmodules/segmentation/output_analysis_semantic.yaml
cosmodules/segmentation/visualization.py
cosmodules/utils/__init__.py
cosmodules/utils/analysis/base_analysis.py
cosmodules/utils/detection/__init__.py
cosmodules/utils/detection/augmentation.py
cosmodules/utils/detection/confusion_matrix.py
cosmodules/utils/detection/tools.py
cosmodules/utils/flow/__init__.py
cosmodules/utils/flow/metrics/__init__.py
cosmodules/utils/flow/metrics/base_metrics.py
cosmodules/utils/flow/metrics/classification_metrics.py
cosmodules/utils/flow/metrics/detection_metrics.py
cosmodules/utils/pipelines/__init__.py
cosmodules/utils/pipelines/export_pipelines.py
cosmodules/utils/pipelines/metrics_pipelines.py
cosmodules/utils/pipelines/plotting_pipelines.py
cosmodules/utils/readme.md
cosmodules-1.1.0.dist-info/licenses/LICENSE
cosmodules-1.1.0.dist-info/METADATA
cosmodules-1.1.0.dist-info/WHEEL
cosmodules-1.1.0.dist-info/RECORD
