Metadata-Version: 2.4
Name: cosmodules
Version: 1.1.0
Summary: 
License: MIT
License-File: LICENSE
Author: bnbsking
Author-email: bnbsking@gmail.com
Requires-Python: >=3.10
Classifier: License :: OSI Approved :: MIT License
Classifier: Programming Language :: Python :: 3
Classifier: Programming Language :: Python :: 3.10
Classifier: Programming Language :: Python :: 3.11
Classifier: Programming Language :: Python :: 3.12
Classifier: Programming Language :: Python :: 3.13
Classifier: Programming Language :: Python :: 3.14
Requires-Dist: matplotlib (>=3.10.7,<4.0.0)
Requires-Dist: opencv-python-headless (>=4.12.0.88,<5.0.0.0)
Requires-Dist: pyyaml (>=6.0.3,<7.0.0)
Requires-Dist: scikit-learn (>=1.7.2,<2.0.0)
Requires-Dist: tqdm (>=4.67.1,<5.0.0)
